sqlalchemy_filterparams/__init__.py
sqlalchemy_filterparams/evaluation.py
sqlalchemy_filterparams/expression.py
sqlalchemy_filterparams/filters.py
sqlalchemy_filterparams/query_binding_configuration.py
sqlalchemy_filterparams/query_config.py
sqlalchemy_filterparams/util.py
sqlalchemy_filterparams-0.9.0.dist-info/DESCRIPTION.rst
sqlalchemy_filterparams-0.9.0.dist-info/METADATA
sqlalchemy_filterparams-0.9.0.dist-info/RECORD
sqlalchemy_filterparams-0.9.0.dist-info/WHEEL
sqlalchemy_filterparams-0.9.0.dist-info/entry_points.txt
sqlalchemy_filterparams-0.9.0.dist-info/metadata.json
sqlalchemy_filterparams-0.9.0.dist-info/namespace_packages.txt
sqlalchemy_filterparams-0.9.0.dist-info/top_level.txt
