Metadata-Version: 2.0
Name: sqlalchemy-filterparams
Version: 0.9.0
Summary: SQLAlchemy Filterparams
Home-page: https://github.com/cbrand/python-sqlalchemy-filterparams
Author: Christoph Brand
Author-email: christoph@brand.rest
License: UNKNOWN
Download-URL: https://github.com/cbrand/python-sqlalchemy-filterparams/tarball/0.9.0
Platform: UNKNOWN
Classifier: Programming Language :: Python
Classifier: Development Status :: 4 - Beta
Classifier: Programming Language :: Python :: 2
Classifier: Programming Language :: Python :: 2.7
Classifier: Programming Language :: Python :: 3
Classifier: Programming Language :: Python :: 3.1
Classifier: Programming Language :: Python :: 3.2
Classifier: Programming Language :: Python :: 3.3
Classifier: Programming Language :: Python :: 3.4
Classifier: Programming Language :: Python :: 3.5
Classifier: License :: OSI Approved :: MIT License
Classifier: Topic :: Database
Requires-Dist: SQLAlchemy
Requires-Dist: filterparams (>=1.0.2)
Requires-Dist: python-dateutil
